lrcgen/__init__.py
lrcgen/__main__.py
lrcgen/api.py
lrcgen/cli.py
lrcgen/config.py
lrcgen/corrector.py
lrcgen/lyrics_aligner.py
lrcgen/utils.py
lrcgen/whisperer.py
lrcgen-0.2.0.dist-info/METADATA
lrcgen-0.2.0.dist-info/WHEEL
lrcgen-0.2.0.dist-info/entry_points.txt
lrcgen-0.2.0.dist-info/top_level.txt
lrcgen-0.2.0.dist-info/RECORD
