Metadata-Version: 2.4
Name: lrcgen
Version: 0.2.0
Summary: AI-powered LRC generator with Whisper and LLM correction
Author: lihan3238
Requires-Python: >=3.8
Requires-Dist: openai-whisper
Requires-Dist: python-dotenv
Provides-Extra: online
Requires-Dist: openai>=1.0; extra == "online"
Provides-Extra: opencc
Requires-Dist: opencc-python-reimplemented; extra == "opencc"
Provides-Extra: full
Requires-Dist: openai>=1.0; extra == "full"
Requires-Dist: opencc-python-reimplemented; extra == "full"
